CBestPractices/README.md
CBestPractices/__init__.py
CBestPractices/__main__.py
CBestPractices/file.epub
CBestPractices/index.html
CBestPractices/css/__init__.py
CBestPractices/css/annotations.css
CBestPractices/css/main.css
CBestPractices/css/normalize.css
CBestPractices/css/popup.css
CBestPractices/font/__init__.py
CBestPractices/font/fontello.eot
CBestPractices/font/fontello.svg
CBestPractices/font/fontello.ttf
CBestPractices/font/fontello.woff
CBestPractices/img/__init__.py
CBestPractices/img/annotator-glyph-sprite.png
CBestPractices/img/annotator-icon-sprite.png
CBestPractices/img/apple-touch-icon.png
CBestPractices/img/cancelfullscreen.png
CBestPractices/img/close.png
CBestPractices/img/fullscreen.png
CBestPractices/img/loader.gif
CBestPractices/img/menu-icon.png
CBestPractices/img/save.png
CBestPractices/img/saved.png
CBestPractices/img/settings-s.png
CBestPractices/img/settings.png
CBestPractices/img/star.png
CBestPractices/js/__init__.py
CBestPractices/js/epub.js
CBestPractices/js/epub.min.js
CBestPractices/js/epub.min.map
CBestPractices/js/hooks.min.js
CBestPractices/js/hooks.min.map
CBestPractices/js/reader.js
CBestPractices/js/reader.js.map
CBestPractices/js/reader.min.js
CBestPractices/js/reader.min.map
CBestPractices/js/hooks/__init__.py
CBestPractices/js/hooks/extensions/__init__.py
CBestPractices/js/hooks/extensions/highlight.js
CBestPractices/js/libs/__init__.py
CBestPractices/js/libs/jquery.min.js
CBestPractices/js/libs/localforage.min.js
CBestPractices/js/libs/screenfull.js
CBestPractices/js/libs/screenfull.min.js
CBestPractices/js/libs/zip.min.js
CBestPractices/js/plugins/__init__.py
CBestPractices/js/plugins/hypothesis.js
CBestPractices/js/plugins/search.js
c_best_practices-2024.3.2.0.dist-info/METADATA
c_best_practices-2024.3.2.0.dist-info/WHEEL
c_best_practices-2024.3.2.0.dist-info/entry_points.txt
c_best_practices-2024.3.2.0.dist-info/top_level.txt
c_best_practices-2024.3.2.0.dist-info/RECORD
